taskiq_fastapi/__init__.py
taskiq_fastapi/initializator.py
taskiq_fastapi/py.typed
taskiq_fastapi-0.3.6.dist-info/METADATA
taskiq_fastapi-0.3.6.dist-info/WHEEL
taskiq_fastapi-0.3.6.dist-info/licenses/LICENSE
taskiq_fastapi-0.3.6.dist-info/RECORD
