Metadata-Version: 2.4
Name: taskiq-fastapi
Version: 0.3.6
Summary: FastAPI integration for taskiq
License: LICENSE
License-File: LICENSE
Keywords: taskiq,tasks,distributed,async,fastapi
Author: Taskiq team
Author-email: taskiq@no-reply.com
Maintainer: Taskiq team
Maintainer-email: taskiq@no-reply.com
Requires-Python: >=3.8.1,<4.0.0
Classifier: Development Status :: 3 - Alpha
Classifier: Intended Audience :: Developers
Classifier: License :: Other/Proprietary License
Classifier: Operating System :: OS Independent
Classifier: Programming Language :: Python
Classifier: Programming Language :: Python :: 3
Classifier: Programming Language :: Python :: 3.9
Classifier: Programming Language :: Python :: 3.10
Classifier: Programming Language :: Python :: 3.11
Classifier: Programming Language :: Python :: 3.12
Classifier: Programming Language :: Python :: 3.13
Classifier: Programming Language :: Python :: 3.14
Classifier: Programming Language :: Python :: 3 :: Only
Classifier: Programming Language :: Python :: 3.8
Classifier: Topic :: System :: Networking
Classifier: Typing :: Typed
Requires-Dist: fastapi (>=0.93.0)
Requires-Dist: taskiq (>=0.8.0,<1)
